flask_classful_apispec/__init__.py
flask_classful_apispec/api_spec.py
flask_classful_apispec/flask_classful_plugin.py
flask_classful_apispec-0.2.0.dist-info/LICENSE
flask_classful_apispec-0.2.0.dist-info/METADATA
flask_classful_apispec-0.2.0.dist-info/WHEEL
flask_classful_apispec-0.2.0.dist-info/top_level.txt
flask_classful_apispec-0.2.0.dist-info/RECORD
